vibecode/__init__.py
vibecode-2.2.0.dist-info/licenses/LICENSE
vibecode-2.2.0.dist-info/METADATA
vibecode-2.2.0.dist-info/WHEEL
vibecode-2.2.0.dist-info/top_level.txt
vibecode-2.2.0.dist-info/RECORD
