Metadata-Version: 2.4
Name: VibeCode
Version: 2.2.0
Summary: A package that embraces vibe coding.
Author-email: Tomasz Badura <tomaszbadurakontakt@gmail.com>
License-Expression: MIT
Project-URL: Homepage, https://github.com/TomaszBadura/VibeCode
Project-URL: Issues, https://github.com/TomaszBadura/VibeCode/Issues
Classifier: Programming Language :: Python :: 3
Classifier: Operating System :: OS Independent
Requires-Python: >=3.9
License-File: LICENSE
Requires-Dist: google-genai
Dynamic: license-file
